XStatic_JQuery.quicksearch-2.0.3.2-py3.6-nspkg.pth
xstatic/pkg/jquery_quicksearch/__init__.py
xstatic/pkg/jquery_quicksearch/data/jquery.quicksearch.js
XStatic_JQuery.quicksearch-2.0.3.2.dist-info/METADATA
XStatic_JQuery.quicksearch-2.0.3.2.dist-info/WHEEL
XStatic_JQuery.quicksearch-2.0.3.2.dist-info/namespace_packages.txt
XStatic_JQuery.quicksearch-2.0.3.2.dist-info/top_level.txt
XStatic_JQuery.quicksearch-2.0.3.2.dist-info/RECORD
