Metadata-Version: 2.1
Name: XStatic-JQuery.quicksearch
Version: 2.0.3.2
Summary: JQuery.quicksearch 2.0.3 (XStatic packaging standard)
Home-page: http://plugins.jquery.com/jquery.quicksearch/
Maintainer: Radomir Dopieralski
Maintainer-email: openstack@sheep.art.pl
License: (same as JQuery.quicksearch)
Keywords: jquery_quicksearch xstatic
Platform: any
